tnypub/__init__.py
tnypub/app.py
tnypub/config.py
tnypub/content.py
tnypub/indexing.py
tnypub/template_functions.py
tnypub/utils.py
tnypub_PaulBeardsell-0.0.1.dist-info/LICENSE
tnypub_PaulBeardsell-0.0.1.dist-info/METADATA
tnypub_PaulBeardsell-0.0.1.dist-info/WHEEL
tnypub_PaulBeardsell-0.0.1.dist-info/top_level.txt
tnypub_PaulBeardsell-0.0.1.dist-info/RECORD
