Metadata-Version: 2.1
Name: tnypub-PaulBeardsell
Version: 0.0.1
Summary: A static stite generator
Home-page: https://tny.pub
Author: PaulBeardsell
Author-email: pbeardsell@gmail.com
License: UNKNOWN
Platform: UNKNOWN
Classifier: Programming Language :: Python :: 3
Classifier: License :: OSI Approved :: MIT License
Classifier: Operating System :: OS Independent
Requires-Python: >=3.8
